shieldmind_client_sdk/__init__.py
shieldmind_client_sdk/client.py
shieldmind_client_sdk/exceptions.py
shieldmind_client_sdk/models.py
shieldmind_client_sdk/py.typed
shieldmind_client_sdk-0.1.0.dist-info/METADATA
shieldmind_client_sdk-0.1.0.dist-info/WHEEL
shieldmind_client_sdk-0.1.0.dist-info/top_level.txt
shieldmind_client_sdk-0.1.0.dist-info/RECORD
