Metadata-Version: 2.4
Name: shieldmind-client-sdk
Version: 0.1.0
Summary: Легковесный Python SDK для валидации LLM запросов через Shieldmind API
Home-page: https://github.com/shieldmind/shieldmind-pro
Author: Shieldmind
Author-email: Shieldmind <support@shieldmind.com>
License: MIT
Project-URL: Homepage, https://github.com/shieldmind/shieldmind-pro
Project-URL: Documentation, https://docs.shieldmind.com
Project-URL: Repository, https://github.com/shieldmind/shieldmind-pro
Project-URL: Issues, https://github.com/shieldmind/shieldmind-pro/issues
Keywords: shieldmind,ai,firewall,security,sdk,api,llm,validation
Classifier: Development Status :: 4 - Beta
Classifier: Intended Audience :: Developers
Classifier: Programming Language :: Python :: 3
Classifier: Programming Language :: Python :: 3.8
Classifier: Programming Language :: Python :: 3.9
Classifier: Programming Language :: Python :: 3.10
Classifier: Programming Language :: Python :: 3.11
Classifier: Programming Language :: Python :: 3.12
Classifier: Topic :: Software Development :: Libraries :: Python Modules
Classifier: Topic :: Security
Requires-Python: >=3.8
Requires-Dist: requests>=2.31.0
Provides-Extra: dev
Requires-Dist: pytest>=7.0.0; extra == "dev"
Requires-Dist: pytest-cov>=4.0.0; extra == "dev"
Requires-Dist: black>=23.0.0; extra == "dev"
Requires-Dist: flake8>=6.0.0; extra == "dev"
Requires-Dist: mypy>=1.0.0; extra == "dev"
Dynamic: author
Dynamic: home-page
Dynamic: requires-python
